factflip/__init__.py
factflip/cli.py
factflip/generators.py
factflip/llms.py
factflip/utils/__init__.py
factflip/utils/build.py
factflip/utils/data.py
factflip/utils/memes.py
factflip/validators.py
factflip-0.2.1.dist-info/LICENSE
factflip-0.2.1.dist-info/METADATA
factflip-0.2.1.dist-info/WHEEL
factflip-0.2.1.dist-info/entry_points.txt
factflip-0.2.1.dist-info/RECORD
