Metadata-Version: 2.1
Name: factflip
Version: 0.2.1
Summary: An image macro meme generator designed for creating fact-checking memes based on misinforming claims and their corrections.
Home-page: https://github.com/evhart/factflip/
License: MIT
Author: Grégoire Burel
Author-email: 423662+evhart@users.noreply.github.com
Requires-Python: >=3.12,<4.0
Classifier: Development Status :: 4 - Beta
Classifier: Environment :: Console
Classifier: Intended Audience :: Developers
Classifier: Intended Audience :: Information Technology
Classifier: Intended Audience :: Science/Research
Classifier: License :: OSI Approved :: MIT License
Classifier: Natural Language :: English
Classifier: Operating System :: OS Independent
Classifier: Programming Language :: Python
Classifier: Programming Language :: Python :: 3
Classifier: Programming Language :: Python :: 3.12
Classifier: Programming Language :: Python :: 3.13
Classifier: Programming Language :: Python :: Implementation :: PyPy
Classifier: Topic :: Multimedia
Classifier: Topic :: Utilities
Requires-Dist: beautifulsoup4 (>=4.12.3,<5.0.0)
Requires-Dist: chromadb (>=0.5.15,<0.6.0)
Requires-Dist: imgflip-py (>=1.0,<2.0)
Requires-Dist: ollama (>=0.3.3,<0.4.0)
Requires-Dist: pandas (>=2.2.3,<3.0.0)
Requires-Dist: platformdirs (>=4.3.6,<5.0.0)
Requires-Dist: python-dotenv (>=1.0.1,<2.0.0)
Requires-Dist: rdflib (>=7.1.0,<8.0.0)
Requires-Dist: requests (>=2.32.3,<3.0.0)
Requires-Dist: rich (>=13.9.2,<14.0.0)
Requires-Dist: sparqlwrapper (>=2.0.0,<3.0.0)
Requires-Dist: typer (>=0.12.5,<0.13.0)
Requires-Dist: usingversion (>=0.1.2,<0.2.0)
Project-URL: Repository, https://github.com/evhart/factflip/
